mcp_server.py
notebookllm_mcp-0.3.0.dist-info/METADATA
notebookllm_mcp-0.3.0.dist-info/WHEEL
notebookllm_mcp-0.3.0.dist-info/entry_points.txt
notebookllm_mcp-0.3.0.dist-info/top_level.txt
notebookllm_mcp-0.3.0.dist-info/RECORD
