Metadata-Version: 2.4
Name: notebookllm_mcp
Version: 0.3.0
Summary: Add your description here
Requires-Python: >=3.10
Requires-Dist: mcp[cli]>=1.8.1
Requires-Dist: notebookllm>=1.1.0
